yt_playlist_dl/__init__.py
yt_playlist_dl/cli.py
yt_playlist_dl/downloader.py
ytplaylist_downloader-0.1.4.dist-info/licenses/LICENSE
ytplaylist_downloader-0.1.4.dist-info/METADATA
ytplaylist_downloader-0.1.4.dist-info/WHEEL
ytplaylist_downloader-0.1.4.dist-info/entry_points.txt
ytplaylist_downloader-0.1.4.dist-info/top_level.txt
ytplaylist_downloader-0.1.4.dist-info/RECORD
